[[1.754832,{"lines":{"0":[[" 14:52:24 up 26 days,  2:15,  1 user,  load average: 0.07, 0.15, 0.16                                                                                        ",{}]],"1":[["                                                                                                                                                             ",{}]],"2":[["                                                                                                                                                             ",{}]],"3":[["                                                                                                                                                             ",{}]],"4":[["                                                                                                                                                             ",{}]],"5":[["                                                                                                                                                             ",{}]],"6":[["                                                                                                                                                             ",{}]],"7":[["                                                                                                                                                             ",{}]],"8":[["                                                                                                                                                             ",{}]],"9":[["                                                                                                                                                             ",{}]],"10":[["                                                                                                                                                             ",{}]],"11":[["                                                                                                                                                             ",{}]],"12":[["                                                                                                                                                             ",{}]],"13":[["                                                                                                                                                             ",{}]],"14":[["                                                                                                                                                             ",{}]],"15":[["                                                                                                                                                             ",{}]],"16":[["                                                                                                                                                             ",{}]],"17":[["                                                                                                                                                             ",{}]],"18":[["                                                                                                                                                             ",{}]],"19":[["                                                                                                                                                             ",{}]],"20":[["                                                                                                                                                             ",{}]],"21":[["                                                                                                                                                             ",{}]],"22":[["                                                                                                                                                             ",{}]],"23":[["                                                                                                                                                             ",{}]],"24":[["                                                                                                                                                             ",{}]],"25":[["                                                                                                                                                             ",{}]],"26":[["                                                                                                                                                             ",{}]],"27":[["                                                                                                                                                             ",{}]],"28":[["                                                                                                                                                             ",{}]],"29":[["                                                                                                                                                             ",{}]],"30":[["                                                                                                                                                             ",{}]],"31":[["                                                                                                                                                             ",{}]],"32":[["                                                                                                                                                             ",{}]],"33":[["                                                                                                                                                             ",{}]],"34":[["                                                                                                                                                             ",{}]],"35":[["                                                                                                                                                             ",{}]],"36":[["                                                                                                                                                             ",{}]],"37":[["                                                                                                                                                             ",{}]],"38":[["                                                                                                                                                             ",{}]],"39":[["                                                                                                                                                             ",{}]],"40":[["                                                                                                                                                             ",{}]],"41":[["                                                                                                                                                             ",{}]],"42":[["                                                                                                                                                             ",{}]],"43":[["                                                                                                                                                             ",{}]],"44":[["                                                                                                                                                             ",{}]],"45":[["                                                                                                                                                             ",{}]],"46":[["                                                                                                                                                             ",{}]],"47":[["                                                                                                                                                             ",{}]],"48":[["                                                                                                                                                             ",{}]],"49":[["                                                                                                                                                             ",{}]],"50":[["                                                                                                                                                             ",{}]],"51":[["                                                                                                                                                             ",{}]],"52":[["                                                                                                                                                             ",{}]]},"cursor":{"x":0,"y":1,"visible":true}}],[0.004152,{"lines":{"1":[["syh",{"fg":4,"bold":true}],["@",{"fg":1}],["grover",{"fg":2,"bold":true}],[":",{}],["~",{"fg":4,"bold":true}],["$                                                                                                                                                ",{}]]},"cursor":{"x":14}}],[5.495519,{"lines":{"1":[["syh",{"fg":4,"bold":true}],["@",{"fg":1}],["grover",{"fg":2,"bold":true}],[":",{}],["~",{"fg":4,"bold":true}],["$ C                                                                                                                                              ",{}]]},"cursor":{"x":15}}],[0.463891,{"lines":{"1":[["syh",{"fg":4,"bold":true}],["@",{"fg":1}],["grover",{"fg":2,"bold":true}],[":",{}],["~",{"fg":4,"bold":true}],["$ Ce                                                                                                                                             ",{}]]},"cursor":{"x":16}}],[0.271991,{"lines":{"1":[["syh",{"fg":4,"bold":true}],["@",{"fg":1}],["grover",{"fg":2,"bold":true}],[":",{}],["~",{"fg":4,"bold":true}],["$ Cec                                                                                                                                            ",{}]]},"cursor":{"x":17}}],[0.16811,{"lines":{"1":[["syh",{"fg":4,"bold":true}],["@",{"fg":1}],["grover",{"fg":2,"bold":true}],[":",{}],["~",{"fg":4,"bold":true}],["$ Ceci                                                                                                                                           ",{}]]},"cursor":{"x":18}}],[0.103897,{"cursor":{"x":19}}],[0.191977,{"lines":{"1":[["syh",{"fg":4,"bold":true}],["@",{"fg":1}],["grover",{"fg":2,"bold":true}],[":",{}],["~",{"fg":4,"bold":true}],["$ Ceci e                                                                                                                                         ",{}]]},"cursor":{"x":20}}],[0.200103,{"lines":{"1":[["syh",{"fg":4,"bold":true}],["@",{"fg":1}],["grover",{"fg":2,"bold":true}],[":",{}],["~",{"fg":4,"bold":true}],["$ Ceci es                                                                                                                                        ",{}]]},"cursor":{"x":21}}],[0.087936,{"lines":{"1":[["syh",{"fg":4,"bold":true}],["@",{"fg":1}],["grover",{"fg":2,"bold":true}],[":",{}],["~",{"fg":4,"bold":true}],["$ Ceci est                                                                                                                                       ",{}]]},"cursor":{"x":22}}],[0.09603399999999999,{"cursor":{"x":23}}],[0.448022,{"lines":{"1":[["syh",{"fg":4,"bold":true}],["@",{"fg":1}],["grover",{"fg":2,"bold":true}],[":",{}],["~",{"fg":4,"bold":true}],["$ Ceci est u                                                                                                                                     ",{}]]},"cursor":{"x":24}}],[0.240039,{"lines":{"1":[["syh",{"fg":4,"bold":true}],["@",{"fg":1}],["grover",{"fg":2,"bold":true}],[":",{}],["~",{"fg":4,"bold":true}],["$ Ceci est un                                                                                                                                    ",{}]]},"cursor":{"x":25}}],[0.063889,{"cursor":{"x":26}}],[0.287935,{"lines":{"1":[["syh",{"fg":4,"bold":true}],["@",{"fg":1}],["grover",{"fg":2,"bold":true}],[":",{}],["~",{"fg":4,"bold":true}],["$ Ceci est un t                                                                                                                                  ",{}]]},"cursor":{"x":27}}],[0.06406199999999999,{"lines":{"1":[["syh",{"fg":4,"bold":true}],["@",{"fg":1}],["grover",{"fg":2,"bold":true}],[":",{}],["~",{"fg":4,"bold":true}],["$ Ceci est un te                                                                                                                                 ",{}]]},"cursor":{"x":28}}],[0.200043,{"lines":{"1":[["syh",{"fg":4,"bold":true}],["@",{"fg":1}],["grover",{"fg":2,"bold":true}],[":",{}],["~",{"fg":4,"bold":true}],["$ Ceci est un tes                                                                                                                                ",{}]]},"cursor":{"x":29}}],[0.111872,{"lines":{"1":[["syh",{"fg":4,"bold":true}],["@",{"fg":1}],["grover",{"fg":2,"bold":true}],[":",{}],["~",{"fg":4,"bold":true}],["$ Ceci est un test                                                                                                                               ",{}]]},"cursor":{"x":30}}],[1.272023,{"lines":{"1":[["syh",{"fg":4,"bold":true}],["@",{"fg":1}],["grover",{"fg":2,"bold":true}],[":",{}],["~",{"fg":4,"bold":true}],["$ Ceci est un tes                                                                                                                                ",{}]]},"cursor":{"x":29}}],[0.499917,{"lines":{"1":[["syh",{"fg":4,"bold":true}],["@",{"fg":1}],["grover",{"fg":2,"bold":true}],[":",{}],["~",{"fg":4,"bold":true}],["$ Ceci est un te                                                                                                                                 ",{}]]},"cursor":{"x":28}}],[0.032008,{"lines":{"1":[["syh",{"fg":4,"bold":true}],["@",{"fg":1}],["grover",{"fg":2,"bold":true}],[":",{}],["~",{"fg":4,"bold":true}],["$ Ceci est un t                                                                                                                                  ",{}]]},"cursor":{"x":27}}],[0.027986,{"lines":{"1":[["syh",{"fg":4,"bold":true}],["@",{"fg":1}],["grover",{"fg":2,"bold":true}],[":",{}],["~",{"fg":4,"bold":true}],["$ Ceci est un                                                                                                                                    ",{}]]},"cursor":{"x":26}}],[0.032159,{"cursor":{"x":25}}],[0.027856,{"lines":{"1":[["syh",{"fg":4,"bold":true}],["@",{"fg":1}],["grover",{"fg":2,"bold":true}],[":",{}],["~",{"fg":4,"bold":true}],["$ Ceci est u                                                                                                                                     ",{}]]},"cursor":{"x":24}}],[0.032239,{"lines":{"1":[["syh",{"fg":4,"bold":true}],["@",{"fg":1}],["grover",{"fg":2,"bold":true}],[":",{}],["~",{"fg":4,"bold":true}],["$ Ceci est                                                                                                                                       ",{}]]},"cursor":{"x":23}}],[0.03174,{"cursor":{"x":22}}],[0.028144,{"lines":{"1":[["syh",{"fg":4,"bold":true}],["@",{"fg":1}],["grover",{"fg":2,"bold":true}],[":",{}],["~",{"fg":4,"bold":true}],["$ Ceci es                                                                                                                                        ",{}]]},"cursor":{"x":21}}],[0.031859,{"lines":{"1":[["syh",{"fg":4,"bold":true}],["@",{"fg":1}],["grover",{"fg":2,"bold":true}],[":",{}],["~",{"fg":4,"bold":true}],["$ Ceci e                                                                                                                                         ",{}]]},"cursor":{"x":20}}],[0.03205,{"lines":{"1":[["syh",{"fg":4,"bold":true}],["@",{"fg":1}],["grover",{"fg":2,"bold":true}],[":",{}],["~",{"fg":4,"bold":true}],["$ Ceci                                                                                                                                           ",{}]]},"cursor":{"x":19}}],[0.031946,{"cursor":{"x":18}}],[0.027989,{"lines":{"1":[["syh",{"fg":4,"bold":true}],["@",{"fg":1}],["grover",{"fg":2,"bold":true}],[":",{}],["~",{"fg":4,"bold":true}],["$ Cec                                                                                                                                            ",{}]]},"cursor":{"x":17}}],[0.028157,{"lines":{"1":[["syh",{"fg":4,"bold":true}],["@",{"fg":1}],["grover",{"fg":2,"bold":true}],[":",{}],["~",{"fg":4,"bold":true}],["$ Ce                                                                                                                                             ",{}]]},"cursor":{"x":16}}],[0.031867,{"lines":{"1":[["syh",{"fg":4,"bold":true}],["@",{"fg":1}],["grover",{"fg":2,"bold":true}],[":",{}],["~",{"fg":4,"bold":true}],["$ C                                                                                                                                              ",{}]]},"cursor":{"x":15}}],[0.027981,{"lines":{"1":[["syh",{"fg":4,"bold":true}],["@",{"fg":1}],["grover",{"fg":2,"bold":true}],[":",{}],["~",{"fg":4,"bold":true}],["$                                                                                                                                                ",{}]]},"cursor":{"x":14}}],[0.031999,{}],[0.027992,{}],[2.584008,{"lines":{"1":[["syh",{"fg":4,"bold":true}],["@",{"fg":1}],["grover",{"fg":2,"bold":true}],[":",{}],["~",{"fg":4,"bold":true}],["$ s                                                                                                                                              ",{}]]},"cursor":{"x":15}}],[0.18799,{"lines":{"1":[["syh",{"fg":4,"bold":true}],["@",{"fg":1}],["grover",{"fg":2,"bold":true}],[":",{}],["~",{"fg":4,"bold":true}],["$ ss                                                                                                                                             ",{}]]},"cursor":{"x":16}}],[0.160034,{"lines":{"1":[["syh",{"fg":4,"bold":true}],["@",{"fg":1}],["grover",{"fg":2,"bold":true}],[":",{}],["~",{"fg":4,"bold":true}],["$ ssh                                                                                                                                            ",{}]]},"cursor":{"x":17}}],[0.127979,{"cursor":{"x":18}}],[0.215902,{"lines":{"1":[["syh",{"fg":4,"bold":true}],["@",{"fg":1}],["grover",{"fg":2,"bold":true}],[":",{}],["~",{"fg":4,"bold":true}],["$ ssh n                                                                                                                                          ",{}]]},"cursor":{"x":19}}],[0.079982,{"lines":{"1":[["syh",{"fg":4,"bold":true}],["@",{"fg":1}],["grover",{"fg":2,"bold":true}],[":",{}],["~",{"fg":4,"bold":true}],["$ ssh na                                                                                                                                         ",{}]]},"cursor":{"x":20}}],[0.272115,{"lines":{"1":[["syh",{"fg":4,"bold":true}],["@",{"fg":1}],["grover",{"fg":2,"bold":true}],[":",{}],["~",{"fg":4,"bold":true}],["$ ssh nas                                                                                                                                        ",{}]]},"cursor":{"x":21}}],[0.279947,{"lines":{"1":[["syh",{"fg":4,"bold":true}],["@",{"fg":1}],["grover",{"fg":2,"bold":true}],[":",{}],["~",{"fg":4,"bold":true}],["$ ssh nas.                                                                                                                                       ",{}]]},"cursor":{"x":22}}],[0.416061,{"lines":{"1":[["syh",{"fg":4,"bold":true}],["@",{"fg":1}],["grover",{"fg":2,"bold":true}],[":",{}],["~",{"fg":4,"bold":true}],["$ ssh nas.p                                                                                                                                      ",{}]]},"cursor":{"x":23}}],[0.207833,{"lines":{"1":[["syh",{"fg":4,"bold":true}],["@",{"fg":1}],["grover",{"fg":2,"bold":true}],[":",{}],["~",{"fg":4,"bold":true}],["$ ssh nas.pr                                                                                                                                     ",{}]]},"cursor":{"x":24}}],[0.432005,{"lines":{"1":[["syh",{"fg":4,"bold":true}],["@",{"fg":1}],["grover",{"fg":2,"bold":true}],[":",{}],["~",{"fg":4,"bold":true}],["$ ssh nas.pri                                                                                                                                    ",{}]]},"cursor":{"x":25}}],[0.09597700000000001,{"lines":{"1":[["syh",{"fg":4,"bold":true}],["@",{"fg":1}],["grover",{"fg":2,"bold":true}],[":",{}],["~",{"fg":4,"bold":true}],["$ ssh nas.priv                                                                                                                                   ",{}]]},"cursor":{"x":26}}],[0.16014,{"cursor":{"x":0,"y":2}}],[0.59621,{"lines":{"2":[["Connection closed by 10.8.0.42                                                                                                                               ",{}]]},"cursor":{"y":3}}],[0.003962,{"lines":{"3":[["syh",{"fg":4,"bold":true}],["@",{"fg":1}],["grover",{"fg":2,"bold":true}],[":",{}],["~",{"fg":4,"bold":true}],["$                                                                                                                                                ",{}]]},"cursor":{"x":14}}],[2.60768,{"lines":{"3":[["syh",{"fg":4,"bold":true}],["@",{"fg":1}],["grover",{"fg":2,"bold":true}],[":",{}],["~",{"fg":4,"bold":true}],["$ ssh nas.priv                                                                                                                                   ",{}]]},"cursor":{"x":26}}],[0.135887,{"cursor":{"x":25}}],[0.500133,{"cursor":{"x":24}}],[0.031853,{"cursor":{"x":23}}],[0.032052,{"cursor":{"x":22}}],[0.027941,{"cursor":{"x":21}}],[0.03212,{"cursor":{"x":20}}],[0.03191,{"cursor":{"x":19}}],[0.423958,{"cursor":{"x":18}}],[0.376021,{"lines":{"3":[["syh",{"fg":4,"bold":true}],["@",{"fg":1}],["grover",{"fg":2,"bold":true}],[":",{}],["~",{"fg":4,"bold":true}],["$ ssh anas.priv                                                                                                                                  ",{}]]},"cursor":{"x":19}}],[0.487979,{"lines":{"3":[["syh",{"fg":4,"bold":true}],["@",{"fg":1}],["grover",{"fg":2,"bold":true}],[":",{}],["~",{"fg":4,"bold":true}],["$ ssh adnas.priv                                                                                                                                 ",{}]]},"cursor":{"x":20}}],[0.199955,{"lines":{"3":[["syh",{"fg":4,"bold":true}],["@",{"fg":1}],["grover",{"fg":2,"bold":true}],[":",{}],["~",{"fg":4,"bold":true}],["$ ssh admnas.priv                                                                                                                                ",{}]]},"cursor":{"x":21}}],[0.807971,{"lines":{"3":[["syh",{"fg":4,"bold":true}],["@",{"fg":1}],["grover",{"fg":2,"bold":true}],[":",{}],["~",{"fg":4,"bold":true}],["$ ssh adminas.priv                                                                                                                               ",{}]]},"cursor":{"x":22}}],[0.215996,{"lines":{"3":[["syh",{"fg":4,"bold":true}],["@",{"fg":1}],["grover",{"fg":2,"bold":true}],[":",{}],["~",{"fg":4,"bold":true}],["$ ssh adminnas.priv                                                                                                                              ",{}]]},"cursor":{"x":23}}],[0.631976,{"lines":{"3":[["syh",{"fg":4,"bold":true}],["@",{"fg":1}],["grover",{"fg":2,"bold":true}],[":",{}],["~",{"fg":4,"bold":true}],["$ ssh admin@nas.priv                                                                                                                             ",{}]]},"cursor":{"x":24}}],[0.264158,{"cursor":{"x":0,"y":4}}],[0.615927,{"lines":{"4":[["admin@nas.priv's password:                                                                                                                                   ",{}]]},"cursor":{"x":27}}],[3.395904,{"cursor":{"x":0,"y":5}}],[0.111977,{"lines":{"0":[["[~] #                                                                                                                                                        ",{}]],"1":[["                                                                                                                                                             ",{}]],"2":[["                                                                                                                                                             ",{}]],"3":[["                                                                                                                                                             ",{}]],"4":[["                                                                                                                                                             ",{}]]},"cursor":{"x":6,"y":0}}],[0.87995,{"lines":{"1":[["[~] #                                                                                                                                                        ",{}]]},"cursor":{"y":1}}],[0.180467,{"lines":{"2":[["[~] #                                                                                                                                                        ",{}]]},"cursor":{"y":2}}],[0.219541,{"lines":{"3":[["[~] #                                                                                                                                                        ",{}]]},"cursor":{"y":3}}],[0.219981,{"lines":{"3":[["[~] # l                                                                                                                                                      ",{}]]},"cursor":{"x":7}}],[0.08000400000000001,{"lines":{"3":[["[~] # ls                                                                                                                                                     ",{}]]},"cursor":{"x":8}}],[0.067984,{"lines":{"4":[["index_default.html                                                                                                                                           ",{}]],"5":[["[~] #                                                                                                                                                        ",{}]]},"cursor":{"x":6,"y":5}}],[2.599931,{"lines":{"5":[["[~] # ls                                                                                                                                                     ",{}]]},"cursor":{"x":8}}],[0.343974,{"lines":{"5":[["[~] # exit                                                                                                                                                   ",{}]]},"cursor":{"x":10}}],[0.467983,{"lines":{"5":[["[~] # cat /opt/etc/dnsmasq.conf                                                                                                                              ",{}]]},"cursor":{"x":31}}],[1.051977,{"lines":{"6":[["# Configuration file for dnsmasq.                                                                                                                            ",{}]],"7":[["#                                                                                                                                                            ",{}]],"8":[["# Format is one option per line, legal options are the same                                                                                                  ",{}]],"9":[["# as the long options legal on the command line. See                                                                                                         ",{}]],"10":[["# \"/usr/sbin/dnsmasq --help\" or \"man 8 dnsmasq\" for details.                                                                                                 ",{}]],"12":[["# Listen on this specific port instead of the standard DNS port                                                                                              ",{}]],"13":[["# (53). Setting this to zero completely disables DNS function,                                                                                               ",{}]],"14":[["# leaving only DHCP and/or TFTP.                                                                                                                             ",{}]],"15":[["#port=5353                                                                                                                                                   ",{}]],"17":[["# The following two options make you a better netizen, since they                                                                                            ",{}]],"18":[["# tell dnsmasq to filter out queries which the public DNS cannot                                                                                             ",{}]],"19":[["# answer, and which load the servers (especially the root servers)                                                                                           ",{}]],"20":[["# unnecessarily. If you have a dial-on-demand link they also stop                                                                                            ",{}]],"21":[["# these requests from bringing up the link unnecessarily.                                                                                                    ",{}]],"23":[["# Never forward plain names (without a dot or domain part)                                                                                                   ",{}]],"24":[["domain-needed                                                                                                                                                ",{}]],"25":[["# Never forward addresses in the non-routed address spaces.                                                                                                  ",{}]],"26":[["bogus-priv                                                                                                                                                   ",{}]],"29":[["# Uncomment this to filter useless windows-originated DNS requests                                                                                           ",{}]],"30":[["# which can trigger dial-on-demand links needlessly.                                                                                                         ",{}]],"31":[["# Note that (amongst othe                                                                                                                                    ",{}]]},"cursor":{"x":25,"y":31}}],[0.016257,{"lines":{"0":[["dhcp-host=00:23:12:FB:C8:9A,airport,10.1.1.2                                                                                                                 ",{}]],"1":[["dhcp-host=7C:03:4C:5E:C7:FB,set:decodeur,decodeur,10.1.1.3,24h                                                                                               ",{}]],"2":[["dhcp-host=6C:50:4D:4D:DA:FB,switch,10.1.1.4                                                                                                                  ",{}]],"3":[["dhcp-host=3C:BD:D8:2E:96:C8,pioneer,10.1.1.5                                                                                                                 ",{}]],"4":[["dhcp-host=00:0D:C5:D9:06:E2,ipcam,10.1.1.6                                                                                                                   ",{}]],"5":[["dhcp-host=00:04:20:28:50:85,squeezebox,10.1.1.7                                                                                                              ",{}]],"6":[["dhcp-host=3C:4A:92:B1:23:3F,hp-photosmart,10.1.1.8                                                                                                           ",{}]],"7":[["#dhcp-host=00:08:9B:C8:47:4C,nas,10.1.1.9                                                                                                                    ",{}]],"8":[["dhcp-host=00:26:B0:F7:B9:64,minisly,10.1.1.10                                                                                                                ",{}]],"9":[["dhcp-host=00:1B:77:A7:07:02,pc-soso,10.1.1.15                                                                                                                ",{}]],"10":[["dhcp-host=A4:67:06:64:F8:64,ipad-sly,10.1.1.20                                                                                                               ",{}]],"11":[["dhcp-host=90:27:E4:13:EA:0E,iphone-sly,10.1.1.21                                                                                                             ",{}]],"12":[["dhcp-host=98:03:D8:70:34:A1,iphone-soso,10.1.1.22                                                                                                            ",{}]],"13":[["                                                                                                                                                             ",{}]],"14":[["                                                                                                                                                             ",{}]],"15":[["# Give a host with Ethernet address 11:22:33:44:55:66 or                                                                                                     ",{}]],"16":[["# 12:34:56:78:90:12 the IP address 192.168.0.60. Dnsmasq will assume                                                                                         ",{}]],"17":[["# that these two Ethernet interfaces will never be in use at the same                                                                                        ",{}]],"18":[["# time, and give the IP address to the second, even if it is already                                                                                         ",{}]],"19":[["# in use by the first. Useful for laptops with wired and wireless                                                                                            ",{}]],"20":[["# addresses.                                                                                                                                                 ",{}]],"21":[["#dhcp-host=11:22:33:44:55:66,12:34:56:78:90:12,192.168.0.60                                                                                                  ",{}]],"23":[["# Give the machine which says its name is \"bert\" IP address                                                                                                  ",{}]],"24":[["# 192.168.0.70 and an infinite lease                                                                                                                         ",{}]],"25":[["#dhcp-host=bert,192.168.0.70,infinite                                                                                                                        ",{}]],"26":[["                                                                                                                                                             ",{}]],"27":[["# Always give the host with client identifier 01:02:02:04                                                                                                    ",{}]],"28":[["# the IP address 192.168.0.60                                                                                                                                ",{}]],"29":[["#dhcp-host=id:01:02:02:04,192.168.0.60                                                                                                                       ",{}]],"30":[["                                                                                                                                                             ",{}]],"31":[["# Always give the host with client identifier \"marjorie\"                                                                                                     ",{}]],"32":[["# the IP address 192.168.0.60                                                                                                                                ",{}]],"33":[["#dhcp-host=id:marjorie,192.168.0.60                                                                                                                          ",{}]],"35":[["# Enable the address given for \"judge\" in /etc/hosts                                                                                                         ",{}]],"36":[["# to be given to a machine presenting the name \"judge\" when                                                                                                  ",{}]],"37":[["# it asks for a DHCP lease.                                                                                                                                  ",{}]],"38":[["#dhcp-host=judge                                                                                                                                             ",{}]],"40":[["# Never offer DHCP service to a machine whose Ethernet                                                                                                       ",{}]],"41":[["# address is 11:22:33:44:55:66                                                                                                                               ",{}]],"42":[["#dhcp-host=11:22:33:44:55:66,ignore                                                                                                                          ",{}]],"44":[["# Ignore any client-id presented by the machine with Ethernet                                                                                                ",{}]],"45":[["# address 11:22:33:44:55:66. This is useful to prevent a machine                                                                                             ",{}]],"46":[["# being treated differently when running under different OS's or                                                                                             ",{}]],"47":[["# between PXE boot and OS boot.                                                                                                                              ",{}]],"48":[["#dhcp-host=11:22:33:44:55:66,id:*                                                                                                                            ",{}]],"50":[["# Send extra options which are tagged as \"red\" to                                                                                                            ",{}]],"51":[["# the machine with Ethernet address 11:22:33:44:55:66                                                                                                        ",{}]],"52":[["#dhcp-hos                                                                                                                                                    ",{}]]},"cursor":{"x":9,"y":52}}],[0.016572,{"lines":{"0":[["#pxe-service=x86PC, \"Boot from local disk\"                                                                                                                   ",{}]],"1":[["                                                                                                                                                             ",{}]],"2":[["# Loads <tftp-root>/pxelinux.0 from dnsmasq TFTP server.                                                                                                     ",{}]],"3":[["#pxe-service=x86PC, \"Install Linux\", pxelinux                                                                                                                ",{}]],"4":[["                                                                                                                                                             ",{}]],"5":[["# Loads <tftp-root>/pxelinux.0 from TFTP server at 1.2.3.4.                                                                                                  ",{}]],"6":[["# Beware this fails on old PXE ROMS.                                                                                                                         ",{}]],"7":[["#pxe-service=x86PC, \"Install Linux\", pxelinux, 1.2.3.4                                                                                                       ",{}]],"8":[["                                                                                                                                                             ",{}]],"9":[["# Use bootserver on network, found my multicast or broadcast.                                                                                                ",{}]],"10":[["#pxe-service=x86PC, \"Install windows from RIS server\", 1                                                                                                     ",{}]],"11":[["                                                                                                                                                             ",{}]],"12":[["# Use bootserver at a known IP address.                                                                                                                      ",{}]],"13":[["#pxe-service=x86PC, \"Install windows from RIS server\", 1, 1.2.3.4                                                                                            ",{}]],"15":[["# If you have multicast-FTP available,                                                                                                                       ",{}]],"16":[["# information for that can be passed in a similar way using options 1                                                                                        ",{}]],"17":[["# to 5. See page 19 of                                                                                                                                       ",{}]],"18":[["# http://download.intel.com/design/archives/wfm/downloads/pxespec.pdf                                                                                        ",{}]],"19":[["                                                                                                                                                             ",{}]],"20":[["                                                                                                                                                             ",{}]],"21":[["# Enable dnsmasq's built-in TFTP server                                                                                                                      ",{}]],"22":[["#enable-tftp                                                                                                                                                 ",{}]],"23":[["                                                                                                                                                             ",{}]],"24":[["# Set the root directory for files available via FTP.                                                                                                        ",{}]],"25":[["#tftp-root=/var/ftpd                                                                                                                                         ",{}]],"27":[["# Make the TFTP server more secure: with this set, only files owned by                                                                                       ",{}]],"28":[["# the user dnsmasq is running as will be send over the net.                                                                                                  ",{}]],"29":[["#tftp-secure                                                                                                                                                 ",{}]],"31":[["# This option stops dnsmasq from negotiating a larger blocksize for TFTP                                                                                     ",{}]],"32":[["# transfers. It will slow things down, but may rescue some broken TFTP                                                                                       ",{}]],"33":[["# clients.                                                                                                                                                   ",{}]],"34":[["#tftp-no-blocksize                                                                                                                                           ",{}]],"35":[["                                                                                                                                                             ",{}]],"36":[["# Set the boot file name only when the \"red\" tag is set.                                                                                                     ",{}]],"37":[["#dhcp-boot=net:red,pxelinux.red-net                                                                                                                          ",{}]],"38":[["                                                                                                                                                             ",{}]],"39":[["# An example of dhcp-boot with an external TFTP server: the name and IP                                                                                      ",{}]],"40":[["# address of the server are given after the filename.                                                                                                        ",{}]],"41":[["# Can fail with old PXE ROMS. Overridden by --pxe-service.                                                                                                   ",{}]],"42":[["#dhcp-boot=/var/ftpd/pxelinux.0,boothost,192.168.0.3                                                                                                         ",{}]],"44":[["# If there are multiple external tftp servers having a same name                                                                                             ",{}]],"45":[["# (using /etc/hosts) then that name can be specified as the                                                                                                  ",{}]],"46":[["# tftp_servername (the third option to dhcp-boot) and in that                                                                                                ",{}]],"47":[["# case dnsmasq resolves this name and returns the resultant IP                                                                                               ",{}]],"48":[["# addresses in round robin fasion. This facility can be used to                                                                                              ",{}]],"49":[["# load balance the tftp load among a set of servers.                                                                                                         ",{}]],"50":[["#dhcp-boot=/var/ftpd/pxelinux.0,boothost,tftp_server_name                                                                                                    ",{}]],"51":[["                                                                                                                                                             ",{}]],"52":[["# Set the limit on DHCP leases, the default is 150                                                                                                           ",{}]]},"cursor":{"x":50}}],[0.003662,{"lines":{"0":[["# config option is used. (Note that expand-hosts does not need to be                                                                                         ",{}]],"1":[["# set for this to work.)                                                                                                                                     ",{}]],"2":[["                                                                                                                                                             ",{}]],"3":[["# A SRV record sending LDAP for the example.com domain to                                                                                                    ",{}]],"4":[["# ldapserver.example.com port 389                                                                                                                            ",{}]],"5":[["#srv-host=_ldap._tcp.example.com,ldapserver.example.com,389                                                                                                  ",{}]],"6":[["                                                                                                                                                             ",{}]],"7":[["# A SRV record sending LDAP for the example.com domain to                                                                                                    ",{}]],"8":[["# ldapserver.example.com port 389 (using domain=)                                                                                                            ",{}]],"9":[["#domain=example.com                                                                                                                                          ",{}]],"10":[["#srv-host=_ldap._tcp,ldapserver.example.com,389                                                                                                              ",{}]],"12":[["# Two SRV records for LDAP, each with different priorities                                                                                                   ",{}]],"13":[["#srv-host=_ldap._tcp.example.com,ldapserver.example.com,389,1                                                                                                ",{}]],"14":[["#srv-host=_ldap._tcp.example.com,ldapserver.example.com,389,2                                                                                                ",{}]],"15":[["                                                                                                                                                             ",{}]],"16":[["# A SRV record indicating that there is no LDAP server for the domain                                                                                        ",{}]],"17":[["# example.com                                                                                                                                                ",{}]],"18":[["#srv-host=_ldap._tcp.example.com                                                                                                                             ",{}]],"20":[["# The following line shows how to make dnsmasq serve an arbitrary PTR                                                                                        ",{}]],"21":[["# record. This is useful for DNS-SD. (Note that the                                                                                                          ",{}]],"22":[["# domain-name expansion done for SRV records _does_not                                                                                                       ",{}]],"23":[["# occur for PTR records.)                                                                                                                                    ",{}]],"24":[["#ptr-record=_http._tcp.dns-sd-services,\"New Employee Page._http._tcp.dns-sd-services\"                                                                        ",{}]],"25":[["                                                                                                                                                             ",{}]],"26":[["# Change the following lines to enable dnsmasq to serve TXT records.                                                                                         ",{}]],"27":[["# These are used for things like SPF and zeroconf. (Note that the                                                                                            ",{}]],"28":[["# domain-name expansion done for SRV records _does_not                                                                                                       ",{}]],"29":[["# occur for TXT records.)                                                                                                                                    ",{}]],"31":[["#Example SPF.                                                                                                                                                ",{}]],"32":[["#txt-record=example.com,\"v=spf1 a -all\"                                                                                                                      ",{}]],"33":[["                                                                                                                                                             ",{}]],"34":[["#Example zeroconf                                                                                                                                            ",{}]],"35":[["#txt-record=_http._tcp.example.com,name=value,paper=A4                                                                                                       ",{}]],"36":[["                                                                                                                                                             ",{}]],"37":[["# Provide an alias for a \"local\" DNS name. Note that this _only_ works                                                                                       ",{}]],"38":[["# for targets which are names from DHCP or /etc/hosts. Give host                                                                                             ",{}]],"39":[["# \"bert\" another name, bertrand                                                                                                                              ",{}]],"40":[["#cname=bertand,bert                                                                                                                                          ",{}]],"41":[["                                                                                                                                                             ",{}]],"42":[["# For debugging purposes, log each DNS query as it passes through                                                                                            ",{}]],"43":[["# dnsmasq.                                                                                                                                                   ",{}]],"44":[["#log-queries                                                                                                                                                 ",{}]],"45":[["                                                                                                                                                             ",{}]],"46":[["# Log lots of extra information about DHCP transactions.                                                                                                     ",{}]],"47":[["log-dhcp                                                                                                                                                     ",{}]],"48":[["                                                                                                                                                             ",{}]],"49":[["# Include a another lot of configuration options.                                                                                                            ",{}]],"50":[["#conf-file=/etc/dnsmasq.more.conf                                                                                                                            ",{}]],"51":[["#conf-dir=/etc/dnsmasq.d                                                                                                                                     ",{}]],"52":[["[~] #                                                                                                                                                        ",{}]]},"cursor":{"x":6}}],[2.363405,{"lines":{"52":[["[~] # cat /opt/etc/dnsmasq.conf                                                                                                                              ",{}]]},"cursor":{"x":31}}],[0.180006,{"lines":{"52":[["[~] # ls                                                                                                                                                     ",{}]]},"cursor":{"x":8}}],[0.167979,{"lines":{"52":[["[~] # exit                                                                                                                                                   ",{}]]},"cursor":{"x":10}}],[0.259993,{"lines":{"52":[["[~] # cat /opt/etc/dnsmasq.conf                                                                                                                              ",{}]]},"cursor":{"x":31}}],[0.311985,{"lines":{"52":[["[~] # cat /opt/etc/dnsmasq-resolver.conf                                                                                                                     ",{}]]},"cursor":{"x":41}}],[0.780079,{"lines":{"0":[["                                                                                                                                                             ",{}]],"1":[["# A SRV record sending LDAP for the example.com domain to                                                                                                    ",{}]],"2":[["# ldapserver.example.com port 389                                                                                                                            ",{}]],"3":[["#srv-host=_ldap._tcp.example.com,ldapserver.example.com,389                                                                                                  ",{}]],"4":[["                                                                                                                                                             ",{}]],"5":[["# A SRV record sending LDAP for the example.com domain to                                                                                                    ",{}]],"6":[["# ldapserver.example.com port 389 (using domain=)                                                                                                            ",{}]],"7":[["#domain=example.com                                                                                                                                          ",{}]],"8":[["#srv-host=_ldap._tcp,ldapserver.example.com,389                                                                                                              ",{}]],"9":[["                                                                                                                                                             ",{}]],"10":[["# Two SRV records for LDAP, each with different priorities                                                                                                   ",{}]],"11":[["#srv-host=_ldap._tcp.example.com,ldapserver.example.com,389,1                                                                                                ",{}]],"12":[["#srv-host=_ldap._tcp.example.com,ldapserver.example.com,389,2                                                                                                ",{}]],"13":[["                                                                                                                                                             ",{}]],"14":[["# A SRV record indicating that there is no LDAP server for the domain                                                                                        ",{}]],"15":[["# example.com                                                                                                                                                ",{}]],"16":[["#srv-host=_ldap._tcp.example.com                                                                                                                             ",{}]],"17":[["                                                                                                                                                             ",{}]],"18":[["# The following line shows how to make dnsmasq serve an arbitrary PTR                                                                                        ",{}]],"19":[["# record. This is useful for DNS-SD. (Note that the                                                                                                          ",{}]],"20":[["# domain-name expansion done for SRV records _does_not                                                                                                       ",{}]],"21":[["# occur for PTR records.)                                                                                                                                    ",{}]],"22":[["#ptr-record=_http._tcp.dns-sd-services,\"New Employee Page._http._tcp.dns-sd-services\"                                                                        ",{}]],"23":[["                                                                                                                                                             ",{}]],"24":[["# Change the following lines to enable dnsmasq to serve TXT records.                                                                                         ",{}]],"25":[["# These are used for things like SPF and zeroconf. (Note that the                                                                                            ",{}]],"26":[["# domain-name expansion done for SRV records _does_not                                                                                                       ",{}]],"27":[["# occur for TXT records.)                                                                                                                                    ",{}]],"28":[["                                                                                                                                                             ",{}]],"29":[["#Example SPF.                                                                                                                                                ",{}]],"30":[["#txt-record=example.com,\"v=spf1 a -all\"                                                                                                                      ",{}]],"31":[["                                                                                                                                                             ",{}]],"32":[["#Example zeroconf                                                                                                                                            ",{}]],"33":[["#txt-record=_http._tcp.example.com,name=value,paper=A4                                                                                                       ",{}]],"34":[["                                                                                                                                                             ",{}]],"35":[["# Provide an alias for a \"local\" DNS name. Note that this _only_ works                                                                                       ",{}]],"36":[["# for targets which are names from DHCP or /etc/hosts. Give host                                                                                             ",{}]],"37":[["# \"bert\" another name, bertrand                                                                                                                              ",{}]],"38":[["#cname=bertand,bert                                                                                                                                          ",{}]],"39":[["                                                                                                                                                             ",{}]],"40":[["# For debugging purposes, log each DNS query as it passes through                                                                                            ",{}]],"41":[["# dnsmasq.                                                                                                                                                   ",{}]],"42":[["#log-queries                                                                                                                                                 ",{}]],"43":[["                                                                                                                                                             ",{}]],"44":[["# Log lots of extra information about DHCP transactions.                                                                                                     ",{}]],"45":[["log-dhcp                                                                                                                                                     ",{}]],"46":[["                                                                                                                                                             ",{}]],"47":[["# Include a another lot of configuration options.                                                                                                            ",{}]],"48":[["#conf-file=/etc/dnsmasq.more.conf                                                                                                                            ",{}]],"49":[["#conf-dir=/etc/dnsmasq.d                                                                                                                                     ",{}]],"50":[["[~] # cat /opt/etc/dnsmasq-resolver.conf                                                                                                                     ",{}]],"51":[["nameserver 10.1.1.1                                                                                                                                          ",{}]],"52":[["[~] #                                                                                                                                                        ",{}]]},"cursor":{"x":6}}],[0.735912,{"lines":{"0":[["# ldapserver.example.com port 389                                                                                                                            ",{}]],"1":[["#srv-host=_ldap._tcp.example.com,ldapserver.example.com,389                                                                                                  ",{}]],"2":[["                                                                                                                                                             ",{}]],"3":[["# A SRV record sending LDAP for the example.com domain to                                                                                                    ",{}]],"4":[["# ldapserver.example.com port 389 (using domain=)                                                                                                            ",{}]],"5":[["#domain=example.com                                                                                                                                          ",{}]],"6":[["#srv-host=_ldap._tcp,ldapserver.example.com,389                                                                                                              ",{}]],"7":[["                                                                                                                                                             ",{}]],"8":[["# Two SRV records for LDAP, each with different priorities                                                                                                   ",{}]],"9":[["#srv-host=_ldap._tcp.example.com,ldapserver.example.com,389,1                                                                                                ",{}]],"10":[["#srv-host=_ldap._tcp.example.com,ldapserver.example.com,389,2                                                                                                ",{}]],"11":[["                                                                                                                                                             ",{}]],"12":[["# A SRV record indicating that there is no LDAP server for the domain                                                                                        ",{}]],"13":[["# example.com                                                                                                                                                ",{}]],"14":[["#srv-host=_ldap._tcp.example.com                                                                                                                             ",{}]],"15":[["                                                                                                                                                             ",{}]],"16":[["# The following line shows how to make dnsmasq serve an arbitrary PTR                                                                                        ",{}]],"17":[["# record. This is useful for DNS-SD. (Note that the                                                                                                          ",{}]],"18":[["# domain-name expansion done for SRV records _does_not                                                                                                       ",{}]],"19":[["# occur for PTR records.)                                                                                                                                    ",{}]],"20":[["#ptr-record=_http._tcp.dns-sd-services,\"New Employee Page._http._tcp.dns-sd-services\"                                                                        ",{}]],"21":[["                                                                                                                                                             ",{}]],"22":[["# Change the following lines to enable dnsmasq to serve TXT records.                                                                                         ",{}]],"23":[["# These are used for things like SPF and zeroconf. (Note that the                                                                                            ",{}]],"24":[["# domain-name expansion done for SRV records _does_not                                                                                                       ",{}]],"25":[["# occur for TXT records.)                                                                                                                                    ",{}]],"26":[["                                                                                                                                                             ",{}]],"27":[["#Example SPF.                                                                                                                                                ",{}]],"28":[["#txt-record=example.com,\"v=spf1 a -all\"                                                                                                                      ",{}]],"29":[["                                                                                                                                                             ",{}]],"30":[["#Example zeroconf                                                                                                                                            ",{}]],"31":[["#txt-record=_http._tcp.example.com,name=value,paper=A4                                                                                                       ",{}]],"32":[["                                                                                                                                                             ",{}]],"33":[["# Provide an alias for a \"local\" DNS name. Note that this _only_ works                                                                                       ",{}]],"34":[["# for targets which are names from DHCP or /etc/hosts. Give host                                                                                             ",{}]],"35":[["# \"bert\" another name, bertrand                                                                                                                              ",{}]],"36":[["#cname=bertand,bert                                                                                                                                          ",{}]],"37":[["                                                                                                                                                             ",{}]],"38":[["# For debugging purposes, log each DNS query as it passes through                                                                                            ",{}]],"39":[["# dnsmasq.                                                                                                                                                   ",{}]],"40":[["#log-queries                                                                                                                                                 ",{}]],"41":[["                                                                                                                                                             ",{}]],"42":[["# Log lots of extra information about DHCP transactions.                                                                                                     ",{}]],"43":[["log-dhcp                                                                                                                                                     ",{}]],"44":[["                                                                                                                                                             ",{}]],"45":[["# Include a another lot of configuration options.                                                                                                            ",{}]],"46":[["#conf-file=/etc/dnsmasq.more.conf                                                                                                                            ",{}]],"47":[["#conf-dir=/etc/dnsmasq.d                                                                                                                                     ",{}]],"48":[["[~] # cat /opt/etc/dnsmasq-resolver.conf                                                                                                                     ",{}]],"49":[["nameserver 10.1.1.1                                                                                                                                          ",{}]],"50":[["[~] # logout                                                                                                                                                 ",{}]],"51":[["Connection to nas.priv closed.                                                                                                                               ",{}]],"52":[["                                                                                                                                                             ",{}]]},"cursor":{"x":0}}],[0.004301,{"lines":{"52":[["syh",{"fg":4,"bold":true}],["@",{"fg":1}],["grover",{"fg":2,"bold":true}],[":",{}],["~",{"fg":4,"bold":true}],["$                                                                                                                                                ",{}]]},"cursor":{"x":14}}],[2.33157,{"lines":{"0":[["#srv-host=_ldap._tcp.example.com,ldapserver.example.com,389                                                                                                  ",{}]],"1":[["                                                                                                                                                             ",{}]],"2":[["# A SRV record sending LDAP for the example.com domain to                                                                                                    ",{}]],"3":[["# ldapserver.example.com port 389 (using domain=)                                                                                                            ",{}]],"4":[["#domain=example.com                                                                                                                                          ",{}]],"5":[["#srv-host=_ldap._tcp,ldapserver.example.com,389                                                                                                              ",{}]],"6":[["                                                                                                                                                             ",{}]],"7":[["# Two SRV records for LDAP, each with different priorities                                                                                                   ",{}]],"8":[["#srv-host=_ldap._tcp.example.com,ldapserver.example.com,389,1                                                                                                ",{}]],"9":[["#srv-host=_ldap._tcp.example.com,ldapserver.example.com,389,2                                                                                                ",{}]],"10":[["                                                                                                                                                             ",{}]],"11":[["# A SRV record indicating that there is no LDAP server for the domain                                                                                        ",{}]],"12":[["# example.com                                                                                                                                                ",{}]],"13":[["#srv-host=_ldap._tcp.example.com                                                                                                                             ",{}]],"14":[["                                                                                                                                                             ",{}]],"15":[["# The following line shows how to make dnsmasq serve an arbitrary PTR                                                                                        ",{}]],"16":[["# record. This is useful for DNS-SD. (Note that the                                                                                                          ",{}]],"17":[["# domain-name expansion done for SRV records _does_not                                                                                                       ",{}]],"18":[["# occur for PTR records.)                                                                                                                                    ",{}]],"19":[["#ptr-record=_http._tcp.dns-sd-services,\"New Employee Page._http._tcp.dns-sd-services\"                                                                        ",{}]],"20":[["                                                                                                                                                             ",{}]],"21":[["# Change the following lines to enable dnsmasq to serve TXT records.                                                                                         ",{}]],"22":[["# These are used for things like SPF and zeroconf. (Note that the                                                                                            ",{}]],"23":[["# domain-name expansion done for SRV records _does_not                                                                                                       ",{}]],"24":[["# occur for TXT records.)                                                                                                                                    ",{}]],"25":[["                                                                                                                                                             ",{}]],"26":[["#Example SPF.                                                                                                                                                ",{}]],"27":[["#txt-record=example.com,\"v=spf1 a -all\"                                                                                                                      ",{}]],"28":[["                                                                                                                                                             ",{}]],"29":[["#Example zeroconf                                                                                                                                            ",{}]],"30":[["#txt-record=_http._tcp.example.com,name=value,paper=A4                                                                                                       ",{}]],"31":[["                                                                                                                                                             ",{}]],"32":[["# Provide an alias for a \"local\" DNS name. Note that this _only_ works                                                                                       ",{}]],"33":[["# for targets which are names from DHCP or /etc/hosts. Give host                                                                                             ",{}]],"34":[["# \"bert\" another name, bertrand                                                                                                                              ",{}]],"35":[["#cname=bertand,bert                                                                                                                                          ",{}]],"36":[["                                                                                                                                                             ",{}]],"37":[["# For debugging purposes, log each DNS query as it passes through                                                                                            ",{}]],"38":[["# dnsmasq.                                                                                                                                                   ",{}]],"39":[["#log-queries                                                                                                                                                 ",{}]],"40":[["                                                                                                                                                             ",{}]],"41":[["# Log lots of extra information about DHCP transactions.                                                                                                     ",{}]],"42":[["log-dhcp                                                                                                                                                     ",{}]],"43":[["                                                                                                                                                             ",{}]],"44":[["# Include a another lot of configuration options.                                                                                                            ",{}]],"45":[["#conf-file=/etc/dnsmasq.more.conf                                                                                                                            ",{}]],"46":[["#conf-dir=/etc/dnsmasq.d                                                                                                                                     ",{}]],"47":[["[~] # cat /opt/etc/dnsmasq-resolver.conf                                                                                                                     ",{}]],"48":[["nameserver 10.1.1.1                                                                                                                                          ",{}]],"49":[["[~] # logout                                                                                                                                                 ",{}]],"50":[["Connection to nas.priv closed.                                                                                                                               ",{}]],"51":[["syh",{"fg":4,"bold":true}],["@",{"fg":1}],["grover",{"fg":2,"bold":true}],[":",{}],["~",{"fg":4,"bold":true}],["$                                                                                                                                                ",{}]]}}],[0.429896,{"lines":{"0":[["                                                                                                                                                             ",{}]],"1":[["# A SRV record sending LDAP for the example.com domain to                                                                                                    ",{}]],"2":[["# ldapserver.example.com port 389 (using domain=)                                                                                                            ",{}]],"3":[["#domain=example.com                                                                                                                                          ",{}]],"4":[["#srv-host=_ldap._tcp,ldapserver.example.com,389                                                                                                              ",{}]],"5":[["                                                                                                                                                             ",{}]],"6":[["# Two SRV records for LDAP, each with different priorities                                                                                                   ",{}]],"7":[["#srv-host=_ldap._tcp.example.com,ldapserver.example.com,389,1                                                                                                ",{}]],"8":[["#srv-host=_ldap._tcp.example.com,ldapserver.example.com,389,2                                                                                                ",{}]],"9":[["                                                                                                                                                             ",{}]],"10":[["# A SRV record indicating that there is no LDAP server for the domain                                                                                        ",{}]],"11":[["# example.com                                                                                                                                                ",{}]],"12":[["#srv-host=_ldap._tcp.example.com                                                                                                                             ",{}]],"13":[["                                                                                                                                                             ",{}]],"14":[["# The following line shows how to make dnsmasq serve an arbitrary PTR                                                                                        ",{}]],"15":[["# record. This is useful for DNS-SD. (Note that the                                                                                                          ",{}]],"16":[["# domain-name expansion done for SRV records _does_not                                                                                                       ",{}]],"17":[["# occur for PTR records.)                                                                                                                                    ",{}]],"18":[["#ptr-record=_http._tcp.dns-sd-services,\"New Employee Page._http._tcp.dns-sd-services\"                                                                        ",{}]],"19":[["                                                                                                                                                             ",{}]],"20":[["# Change the following lines to enable dnsmasq to serve TXT records.                                                                                         ",{}]],"21":[["# These are used for things like SPF and zeroconf. (Note that the                                                                                            ",{}]],"22":[["# domain-name expansion done for SRV records _does_not                                                                                                       ",{}]],"23":[["# occur for TXT records.)                                                                                                                                    ",{}]],"24":[["                                                                                                                                                             ",{}]],"25":[["#Example SPF.                                                                                                                                                ",{}]],"26":[["#txt-record=example.com,\"v=spf1 a -all\"                                                                                                                      ",{}]],"27":[["                                                                                                                                                             ",{}]],"28":[["#Example zeroconf                                                                                                                                            ",{}]],"29":[["#txt-record=_http._tcp.example.com,name=value,paper=A4                                                                                                       ",{}]],"30":[["                                                                                                                                                             ",{}]],"31":[["# Provide an alias for a \"local\" DNS name. Note that this _only_ works                                                                                       ",{}]],"32":[["# for targets which are names from DHCP or /etc/hosts. Give host                                                                                             ",{}]],"33":[["# \"bert\" another name, bertrand                                                                                                                              ",{}]],"34":[["#cname=bertand,bert                                                                                                                                          ",{}]],"35":[["                                                                                                                                                             ",{}]],"36":[["# For debugging purposes, log each DNS query as it passes through                                                                                            ",{}]],"37":[["# dnsmasq.                                                                                                                                                   ",{}]],"38":[["#log-queries                                                                                                                                                 ",{}]],"39":[["                                                                                                                                                             ",{}]],"40":[["# Log lots of extra information about DHCP transactions.                                                                                                     ",{}]],"41":[["log-dhcp                                                                                                                                                     ",{}]],"42":[["                                                                                                                                                             ",{}]],"43":[["# Include a another lot of configuration options.                                                                                                            ",{}]],"44":[["#conf-file=/etc/dnsmasq.more.conf                                                                                                                            ",{}]],"45":[["#conf-dir=/etc/dnsmasq.d                                                                                                                                     ",{}]],"46":[["[~] # cat /opt/etc/dnsmasq-resolver.conf                                                                                                                     ",{}]],"47":[["nameserver 10.1.1.1                                                                                                                                          ",{}]],"48":[["[~] # logout                                                                                                                                                 ",{}]],"49":[["Connection to nas.priv closed.                                                                                                                               ",{}]],"50":[["syh",{"fg":4,"bold":true}],["@",{"fg":1}],["grover",{"fg":2,"bold":true}],[":",{}],["~",{"fg":4,"bold":true}],["$                                                                                                                                                ",{}]],"51":[["syh",{"fg":4,"bold":true}],["@",{"fg":1}],["grover",{"fg":2,"bold":true}],[":",{}],["~",{"fg":4,"bold":true}],["$ exit                                                                                                                                           ",{}]],"52":[["                                                                                                                                                             ",{}]]},"cursor":{"x":0}}]]